lero/__init__.py
lero/__main__.py
lero/dataset_editor/__init__.py
lero/dataset_editor/cli.py
lero/dataset_editor/constants.py
lero/dataset_editor/core.py
lero/dataset_editor/display.py
lero/dataset_editor/file_utils.py
lero/dataset_editor/metadata.py
lero/dataset_editor/operations.py
lero/gui/__init__.py
lero/gui/constants.py
lero/gui/controls.py
lero/gui/data_handler.py
lero/gui/plot_component.py
lero/gui/video_component.py
lero/gui/viewer.py
lero_core-0.3.0.dist-info/METADATA
lero_core-0.3.0.dist-info/WHEEL
lero_core-0.3.0.dist-info/entry_points.txt
lero_core-0.3.0.dist-info/licenses/LICENSE
lero_core-0.3.0.dist-info/RECORD
