Metadata-Version: 2.4
Name: lero-core
Version: 0.3.0
Summary: LERO - LeRobot dataset Operations toolkit for editing and managing LeRobot datasets
Project-URL: Homepage, https://github.com/masato-ka/lero
Project-URL: Repository, https://github.com/masato-ka/lero
Project-URL: Documentation, https://github.com/masato-ka/lero#readme
Project-URL: Issues, https://github.com/example/masato-ka/issues
Author-email: masato-ka <jp6uzv@gmail.com>
License-Expression: Apache-2.0
License-File: LICENSE
Keywords: dataset,imitation-learning,lerobot,machine-learning,robotics
Classifier: Development Status :: 4 - Beta
Classifier: Intended Audience :: Science/Research
Classifier: License :: OSI Approved :: Apache Software License
Classifier: Programming Language :: Python :: 3
Classifier: Programming Language :: Python :: 3.8
Classifier: Programming Language :: Python :: 3.9
Classifier: Programming Language :: Python :: 3.10
Classifier: Programming Language :: Python :: 3.11
Classifier: Programming Language :: Python :: 3.12
Classifier: Topic :: Scientific/Engineering :: Artificial Intelligence
Classifier: Topic :: Software Development :: Libraries :: Python Modules
Requires-Python: >=3.8
Requires-Dist: pandas>=1.5.0
Requires-Dist: pyarrow>=10.0.0
Provides-Extra: dev
Requires-Dist: black>=22.0.0; extra == 'dev'
Requires-Dist: flake8>=5.0.0; extra == 'dev'
Requires-Dist: isort>=5.10.0; extra == 'dev'
Requires-Dist: mypy>=1.0.0; extra == 'dev'
Requires-Dist: pytest-cov>=4.0.0; extra == 'dev'
Requires-Dist: pytest>=7.0.0; extra == 'dev'
Provides-Extra: gui
Requires-Dist: matplotlib>=3.5.0; extra == 'gui'
Requires-Dist: opencv-python>=4.5.0; extra == 'gui'
Requires-Dist: pillow>=8.0.0; extra == 'gui'
